remotecode/__init__.py
remotecode-0.1.2.dist-info/DESCRIPTION.rst
remotecode-0.1.2.dist-info/METADATA
remotecode-0.1.2.dist-info/RECORD
remotecode-0.1.2.dist-info/WHEEL
remotecode-0.1.2.dist-info/metadata.json
remotecode-0.1.2.dist-info/top_level.txt
