Metadata-Version: 2.0
Name: remotecode
Version: 0.1.2
Summary: **DEPRECATED** A Sphinx extension that enables remote code blocks
Home-page: https://github.com/kallimachos/remotecode
Author: Brian moss
Author-email: kallimachos@gmail.com
License: GPLv3
Keywords: sphinx documentation remote code block
Platform: UNKNOWN
Classifier: Development Status :: 4 - Beta
Classifier: Intended Audience :: Developers
Classifier: Topic :: Documentation :: Sphinx
Classifier: Framework :: Sphinx :: Extension
Classifier: License :: OSI Approved :: GNU General Public License v3 (GPLv3)
Classifier: Programming Language :: Python :: 2
Classifier: Programming Language :: Python :: 2.7
Classifier: Programming Language :: Python :: 3
Classifier: Programming Language :: Python :: 3.4
Requires-Dist: requests
